pyray/__init__.py
pyray/__init__.pyi
pyray/py.typed
raylib/__init__.py
raylib/__init__.pyi
raylib/_raylib_cffi.cpython-310-aarch64-linux-gnu.so
raylib/build.py
raylib/colors.py
raylib/defines.py
raylib/enums.py
raylib/glfw3.h.modified
raylib/physac.h.modified
raylib/py.typed
raylib/raygui.h.modified
raylib/raylib.h.modified
raylib/raymath.h.modified
raylib/rlgl.h.modified
raylib/version.py
raylib_sdl-5.5.0.4.dist-info/LICENSE
raylib_sdl-5.5.0.4.dist-info/METADATA
raylib_sdl-5.5.0.4.dist-info/WHEEL
raylib_sdl-5.5.0.4.dist-info/top_level.txt
raylib_sdl-5.5.0.4.dist-info/RECORD
